setup.py
dicthistory/__init__.py
dicthistory/history.py
dicthistory.egg-info/PKG-INFO
dicthistory.egg-info/SOURCES.txt
dicthistory.egg-info/dependency_links.txt
dicthistory.egg-info/not-zip-safe
dicthistory.egg-info/top_level.txt