Metadata-Version: 1.0
Name: dicthistory
Version: 1.0
Summary: Store dict contents and hashes on a file
Home-page: UNKNOWN
Author: Aureus Analytics
Author-email: raj@aureusanalytics.com
License: MIT
Platform: UNKNOWN
